CHANGES.rst
DESCRIPTION.rst
MANIFEST.in
README.md
setup.py
src/wai.lazypip.egg-info/PKG-INFO
src/wai.lazypip.egg-info/SOURCES.txt
src/wai.lazypip.egg-info/dependency_links.txt
src/wai.lazypip.egg-info/namespace_packages.txt
src/wai.lazypip.egg-info/requires.txt
src/wai.lazypip.egg-info/top_level.txt
src/wai/lazypip/__init__.py
src/wai/lazypip/_check.py
src/wai/lazypip/_venv.py