Metadata-Version: 1.1
Name: wai.lazypip
Version: 0.0.1
Summary: Allows installation of additional packages (from within virtual environments) at runtime.
Home-page: https://github.com/wai-lazypip
Author: Peter Reutemann
Author-email: fracpete@waikato.ac.nz
License: Apache 2.0 License
Platform: UNKNOWN
Classifier: Development Status :: 4 - Beta
Classifier: License :: OSI Approved :: Apache Software License
Classifier: Topic :: Software Development :: Libraries
Classifier: Programming Language :: Python :: 3
